api/__init__.py
api/admin.py
api/apps.py
api/managers.py
api/models.py
api/permissions.py
api/serializers.py
api/tests.py
api/urls.py
api/validators.py
api/views.py
api/migrations/0001_initial.py
api/migrations/0002_alter_voucher_code.py
api/migrations/0003_applicant_place_of_birth.py
api/migrations/0004_alter_applicant_passport_photo.py
api/migrations/0005_alter_application_voucher.py
api/migrations/0006_remove_application_created_at_and_more.py
api/migrations/0007_alter_document_file.py
api/migrations/__init__.py
application_api-0.3.dist-info/LICENSE
application_api-0.3.dist-info/METADATA
application_api-0.3.dist-info/WHEEL
application_api-0.3.dist-info/top_level.txt
application_api-0.3.dist-info/RECORD
